datarules/__init__.py
datarules/check.py
datarules/context.py
datarules/correction.py
datarules/decorators.py
datarules/eval_utils.py
datarules/lists.py
datarules/primitives.py
datarules/report.py
datarules/rule.py
datarules/utilities.py
datarules/expression/__init__.py
datarules/expression/expressionchecker.py
datarules/expression/expressioncollector.py
datarules/expression/expressionrewriter.py
datarules-0.2.2.dist-info/licenses/LICENSE
datarules-0.2.2.dist-info/METADATA
datarules-0.2.2.dist-info/WHEEL
datarules-0.2.2.dist-info/top_level.txt
datarules-0.2.2.dist-info/RECORD
