Metadata-Version: 2.4
Name: datarules
Version: 0.2.2
Summary: Rules for validating and correcting datasets
Author-email: lverweijen <lauwerund@gmail.com>
License-Expression: Apache-2.0
Project-URL: Homepage, https://github.com/lverweijen/datarules
Project-URL: Repository, https://github.com/lverweijen/datarules
Project-URL: Issues, https://github.com/lverweijen/datarules/issues
Project-URL: Changes, https://github.com/lverweijen/datarules/blob/main/changes.md
Keywords: rules,validation,checks,correction,data-editing,data-cleaning,data-cleansing
Classifier: Intended Audience :: Science/Research
Classifier: Operating System :: OS Independent
Classifier: Programming Language :: Python :: 3
Classifier: Programming Language :: Python :: 3.10
Classifier: Programming Language :: Python :: 3.11
Classifier: Programming Language :: Python :: 3.12
Classifier: Typing :: Typed
Requires-Python: >=3.10
License-File: LICENSE
Requires-Dist: pandas>=1.5.0
Requires-Dist: uneval>=0.2.0
Provides-Extra: extras
Requires-Dist: pyaml; extra == "extras"
Dynamic: license-file
